LICENSE
README.md
setup.py
pymedia/__init__.py
pymedia/pinterest.py
pymedials.egg-info/PKG-INFO
pymedials.egg-info/SOURCES.txt
pymedials.egg-info/dependency_links.txt
pymedials.egg-info/requires.txt
pymedials.egg-info/top_level.txt