Metadata-Version: 2.1
Name: pymedials
Version: 0.1.0
Summary: A Python library for downloading images from Pinterest
Home-page: https://github.com/MrTG-CodeBot
Author: Amal nath
Author-email: amalnath0600@gmail.com
License: UNKNOWN
Platform: UNKNOWN
License-File: LICENSE
